[
    {
        "key": "dbln",
        "value": "%7B%22100042578690141%22%3A%22RIOmNaTB%22%2C%22100093287628914%22%3A%22CD4ODGKD%22%2C%2261557891726175%22%3A%22XXLQ5fJZ%22%2C%2261562446018027%22%3A%22aY5FxBZy%22%2C%2261557771455780%22%3A%22b8RSEfuI%22%2C%22100093863409908%22%3A%22FXX7PVi4%22%2C%2261552638328222%22%3A%228qo9WK3R%22%7D",
        "domain": "facebook.com",
        "path": "/login/device-based/",
        "hostOnly": false,
        "creation": "2024-08-21T05:20:21.674Z",
        "lastAccessed": "2024-08-21T05:20:21.674Z"
    },
    {
        "key": "sb",
        "value": "MdS5Zqm3zv6m0mRl7pJa5qGQ",
        "domain": "facebook.com",
        "path": "/",
        "hostOnly": false,
        "creation": "2024-08-21T05:20:21.674Z",
        "lastAccessed": "2024-08-21T05:20:21.674Z"
    },
    {
        "key": "datr",
        "value": "MdS5Zg2q2Bkk2VfyRjcWcJlx",
        "domain": "facebook.com",
        "path": "/",
        "hostOnly": false,
        "creation": "2024-08-21T05:20:21.674Z",
        "lastAccessed": "2024-08-21T05:20:21.674Z"
    },
    {
        "key": "ps_l",
        "value": "1",
        "domain": "facebook.com",
        "path": "/",
        "hostOnly": false,
        "creation": "2024-08-21T05:20:21.674Z",
        "lastAccessed": "2024-08-21T05:20:21.674Z"
    },
    {
        "key": "ps_n",
        "value": "1",
        "domain": "facebook.com",
        "path": "/",
        "hostOnly": false,
        "creation": "2024-08-21T05:20:21.674Z",
        "lastAccessed": "2024-08-21T05:20:21.674Z"
    },
    {
        "key": "locale",
        "value": "en_GB",
        "domain": "facebook.com",
        "path": "/",
        "hostOnly": false,
        "creation": "2024-08-21T05:20:21.674Z",
        "lastAccessed": "2024-08-21T05:20:21.674Z"
    },
    {
        "key": "vpd",
        "value": "v1%3B589x336x2.139572858810425",
        "domain": "facebook.com",
        "path": "/",
        "hostOnly": false,
        "creation": "2024-08-21T05:20:21.674Z",
        "lastAccessed": "2024-08-21T05:20:21.674Z"
    },
    {
        "key": "c_user",
        "value": "61552638328222",
        "domain": "facebook.com",
        "path": "/",
        "hostOnly": false,
        "creation": "2024-08-21T05:20:21.674Z",
        "lastAccessed": "2024-08-21T05:20:21.674Z"
    },
    {
        "key": "fr",
        "value": "0CPFPdiS1MLoDYsUe.AWVv9Kvi1Djj516w-NPSLcoJkOA.BmfS0v..AAA.0.0.BmxJEt.AWX1LkOuW1M",
        "domain": "facebook.com",
        "path": "/",
        "hostOnly": false,
        "creation": "2024-08-21T05:20:21.674Z",
        "lastAccessed": "2024-08-21T05:20:21.674Z"
    },
    {
        "key": "xs",
        "value": "17%3ApQyQkNSSnJNLhQ%3A2%3A1724158254%3A-1%3A4131",
        "domain": "facebook.com",
        "path": "/",
        "hostOnly": false,
        "creation": "2024-08-21T05:20:21.674Z",
        "lastAccessed": "2024-08-21T05:20:21.674Z"
    },
    {
        "key": "m_page_voice",
        "value": "61552638328222",
        "domain": "facebook.com",
        "path": "/",
        "hostOnly": false,
        "creation": "2024-08-21T05:20:21.674Z",
        "lastAccessed": "2024-08-21T05:20:21.674Z"
    },
    {
        "key": "m_pixel_ratio",
        "value": "2.139572858810425",
        "domain": "facebook.com",
        "path": "/",
        "hostOnly": false,
        "creation": "2024-08-21T05:20:21.674Z",
        "lastAccessed": "2024-08-21T05:20:21.674Z"
    },
    {
        "key": "wd",
        "value": "337x641",
        "domain": "facebook.com",
        "path": "/",
        "hostOnly": false,
        "creation": "2024-08-21T05:20:21.674Z",
        "lastAccessed": "2024-08-21T05:20:21.674Z"
    },
    {
        "key": "fbl_st",
        "value": "101325803%3BT%3A28736960",
        "domain": "facebook.com",
        "path": "/",
        "hostOnly": false,
        "creation": "2024-08-21T05:20:21.674Z",
        "lastAccessed": "2024-08-21T05:20:21.674Z"
    },
    {
        "key": "wl_cbv",
        "value": "v2%3Bclient_version%3A2599%3Btimestamp%3A1724217604",
        "domain": "facebook.com",
        "path": "/",
        "hostOnly": false,
        "creation": "2024-08-21T05:20:21.674Z",
        "lastAccessed": "2024-08-21T05:20:21.674Z"
    }
        ]
